libhgdb.so
hgdb-replay
hgdb-rewrite-vcd
hgdb-db
libhgdb-0.1.4.data/scripts/hgdb-replay
libhgdb-0.1.4.data/scripts/hgdb-rewrite-vcd
libhgdb-0.1.4.data/scripts/hgdb-vsim
libhgdb-0.1.4.data/scripts/hgdb-verilator
libhgdb-0.1.4.data/scripts/hgdb-xrun
libhgdb-0.1.4.data/scripts/hgdb-vvp
libhgdb-0.1.4.data/scripts/hgdb-db
libhgdb-0.1.4.data/scripts/hgdb-vcs
libhgdb-0.1.4.dist-info/WHEEL
libhgdb-0.1.4.dist-info/top_level.txt
libhgdb-0.1.4.dist-info/RECORD
libhgdb-0.1.4.dist-info/LICENSE
libhgdb-0.1.4.dist-info/METADATA
libhgdb.libs/libhgdb-8547d05b.so
