Metadata-Version: 2.1
Name: libhgdb
Version: 0.1.4
Summary: UNKNOWN
Home-page: https://github.com/Kuree/hgdb
Author: Keyi Zhang
Author-email: keyi@cs.stanford.edu
License: UNKNOWN
Platform: UNKNOWN
Requires-Python: >=3.6
License-File: LICENSE
